genanki/__init__.py
genanki/apkg_col.py
genanki/apkg_schema.py
genanki/builtin_models.py
genanki/card.py
genanki/deck.py
genanki/model.py
genanki/note.py
genanki/package.py
genanki/util.py
genanki/version.py
genanki_noyaml-0.12.5.dist-info/LICENSE.txt
genanki_noyaml-0.12.5.dist-info/METADATA
genanki_noyaml-0.12.5.dist-info/WHEEL
genanki_noyaml-0.12.5.dist-info/top_level.txt
genanki_noyaml-0.12.5.dist-info/RECORD
